quadrille/__init__.py
quadrille/__main__.py
quadrille/cogol.py
quadrille/network.py
quadrille/version.py
quadrille/data/logger.ini
quadrille-0.1.0.dist-info/LICENSE
quadrille-0.1.0.dist-info/METADATA
quadrille-0.1.0.dist-info/WHEEL
quadrille-0.1.0.dist-info/entry_points.txt
quadrille-0.1.0.dist-info/top_level.txt
quadrille-0.1.0.dist-info/RECORD
